gamecontrollermt/__init__.py
gamecontrollermt/mapLoader.py
gamecontrollermt/pgc.py
gamecontrollermt/predefined_classes.py
gamecontrollermt/start.py
gamecontrollermt-1.2.18.dist-info/DESCRIPTION.rst
gamecontrollermt-1.2.18.dist-info/METADATA
gamecontrollermt-1.2.18.dist-info/RECORD
gamecontrollermt-1.2.18.dist-info/WHEEL
gamecontrollermt-1.2.18.dist-info/metadata.json
gamecontrollermt-1.2.18.dist-info/top_level.txt
