Metadata-Version: 2.0
Name: gamecontrollermt
Version: 1.2.18
Summary: Practical part of Master thesis. Rea-time game controller for games created in pygame, using this package.
Home-page: https://github.com/PaulliDev/gamecontrollermt
Author: Pavol Megela
Author-email: pavol.megela@gmail.com
License: UNKNOWN
Keywords: gamecontrollermt
Platform: UNKNOWN
Classifier: Development Status :: 2 - Pre-Alpha
Classifier: Intended Audience :: Developers
Classifier: Natural Language :: English
Classifier: Programming Language :: Python :: 2
Classifier: Programming Language :: Python :: 2.6
Classifier: Programming Language :: Python :: 2.7
Classifier: Programming Language :: Python :: 3
Classifier: Programming Language :: Python :: 3.3
Classifier: Programming Language :: Python :: 3.4
Classifier: Programming Language :: Python :: 3.5
